cklauth/__init__.py
cklauth/admin.py
cklauth/apps.py
cklauth/auth.py
cklauth/constants.py
cklauth/models.py
cklauth/urls.py
cklauth/utils.py
cklauth/views.py
cklauth/api/__init__.py
cklauth/api/urls.py
cklauth/api/v1/__init__.py
cklauth/api/v1/serializers.py
cklauth/api/v1/urls.py
cklauth/api/v1/views.py
cklauth/migrations/0001_initial.py
cklauth/migrations/__init__.py
cklauth-0.4.0.dist-info/METADATA
cklauth-0.4.0.dist-info/WHEEL
cklauth-0.4.0.dist-info/top_level.txt
cklauth-0.4.0.dist-info/RECORD
