Metadata-Version: 2.1
Name: cklauth
Version: 0.4.0
Summary: An opinionated Django app to provide user authentication.
Home-page: https://github.com/CheesecakeLabs/ckl-rest-auth
Author: Cheesecake Labs
License: BSD License
Platform: UNKNOWN
Classifier: Environment :: Web Environment
Classifier: Framework :: Django
Classifier: Framework :: Django :: 2.1
Classifier: Intended Audience :: Developers
Classifier: License :: OSI Approved :: BSD License
Classifier: Operating System :: OS Independent
Classifier: Programming Language :: Python
Classifier: Programming Language :: Python :: 3.7
Classifier: Topic :: Internet :: WWW/HTTP
Classifier: Topic :: Internet :: WWW/HTTP :: Dynamic Content
Requires-Dist: Django (>=2.1)
Requires-Dist: djangorestframework (>=3.9)
Requires-Dist: django-cors-headers (>=3.0)
Requires-Dist: requests (>=2.18)
